openfl/__init__.py
openfl/__version__.py
openfl/callbacks/__init__.py
openfl/callbacks/callback.py
openfl/callbacks/callback_list.py
openfl/callbacks/lambda_callback.py
openfl/callbacks/memory_profiler.py
openfl/callbacks/metric_writer.py
openfl/callbacks/secure_aggregation.py
openfl/component/__init__.py
openfl/component/aggregator/__init__.py
openfl/component/aggregator/aggregator.py
openfl/component/aggregator/straggler_handling.py
openfl/component/assigner/__init__.py
openfl/component/assigner/assigner.py
openfl/component/assigner/custom_assigner.py
openfl/component/assigner/random_grouped_assigner.py
openfl/component/assigner/static_grouped_assigner.py
openfl/component/assigner/tasks.py
openfl/component/collaborator/__init__.py
openfl/component/collaborator/collaborator.py
openfl/cryptography/__init__.py
openfl/cryptography/ca.py
openfl/cryptography/io.py
openfl/cryptography/participant.py
openfl/databases/__init__.py
openfl/databases/persistent_db.py
openfl/databases/tensor_db.py
openfl/databases/utilities/__init__.py
openfl/databases/utilities/dataframe.py
openfl/experimental/__init__.py
openfl/experimental/workflow/__init__.py
openfl/experimental/workflow/component/__init__.py
openfl/experimental/workflow/component/aggregator/__init__.py
openfl/experimental/workflow/component/aggregator/aggregator.py
openfl/experimental/workflow/component/collaborator/__init__.py
openfl/experimental/workflow/component/collaborator/collaborator.py
openfl/experimental/workflow/component/director/__init__.py
openfl/experimental/workflow/component/director/director.py
openfl/experimental/workflow/component/director/experiment.py
openfl/experimental/workflow/component/envoy/__init__.py
openfl/experimental/workflow/component/envoy/envoy.py
openfl/experimental/workflow/federated/__init__.py
openfl/experimental/workflow/federated/plan/__init__.py
openfl/experimental/workflow/federated/plan/plan.py
openfl/experimental/workflow/interface/__init__.py
openfl_nightly_testing_01-1.9.0.dev2025040811.dist-info/licenses/LICENSE
openfl_nightly_testing_01-1.9.0.dev2025040811.dist-info/licenses/LICENSE-3RD-PARTY
openfl_nightly_testing_01-1.9.0.dev2025040811.dist-info/METADATA
openfl_nightly_testing_01-1.9.0.dev2025040811.dist-info/WHEEL
openfl_nightly_testing_01-1.9.0.dev2025040811.dist-info/entry_points.txt
openfl_nightly_testing_01-1.9.0.dev2025040811.dist-info/top_level.txt
openfl_nightly_testing_01-1.9.0.dev2025040811.dist-info/RECORD
